spotify_uri/__init__.py
spotify_uri/album.py
spotify_uri/artist.py
spotify_uri/episode.py
spotify_uri/local.py
spotify_uri/parse.py
spotify_uri/playlist.py
spotify_uri/search.py
spotify_uri/show.py
spotify_uri/spotify.py
spotify_uri/track.py
spotify_uri/user.py
spotify_uri/util.py
spotify_uri-1.0.3.dist-info/LICENSE
spotify_uri-1.0.3.dist-info/METADATA
spotify_uri-1.0.3.dist-info/WHEEL
spotify_uri-1.0.3.dist-info/top_level.txt
spotify_uri-1.0.3.dist-info/RECORD
