Metadata-Version: 2.1
Name: spotify-uri
Version: 1.0.3
Summary: This project port "@TooTallNate/spotify-uri" to Python.
Home-page: https://github.com/zeroday0619/pyspotify-uri
Author: zeroday0619
Author-email: zeroday0619_dev@outlook.com
License: MIT
Keywords: spotify,spotify-uri
Platform: UNKNOWN
Classifier: Programming Language :: Python :: 3.7
Classifier: Programming Language :: Python :: 3.8
Classifier: Programming Language :: Python :: 3.9
Requires-Python: >=3
